{
  "lastCursor": "1782130029993",
  "plays": [
    {
      "track": "Seigfried",
      "artists": "Frank Ocean",
      "durationMs": 334570,
      "playedAt": "2026-06-22T12:07:09.993Z"
    },
    {
      "track": "Designer",
      "artists": "Tokyo Tea Room",
      "durationMs": 226298,
      "playedAt": "2026-06-22T12:01:41.099Z"
    },
    {
      "track": "These Chains",
      "artists": "Mid-Air Thief",
      "durationMs": 307700,
      "playedAt": "2026-06-22T03:26:19.409Z"
    },
    {
      "track": "Binary Data XXXV",
      "artists": "Alfonso Peduto",
      "durationMs": 346999,
      "playedAt": "2026-06-22T03:22:29.014Z"
    },
    {
      "track": "Music To Walk Home By",
      "artists": "Tame Impala",
      "durationMs": 312213,
      "playedAt": "2026-06-22T02:53:23.851Z"
    },
    {
      "track": "Swangin’ On Westheimer",
      "artists": "Don Toliver",
      "durationMs": 288852,
      "playedAt": "2026-06-22T02:48:17.358Z"
    },
    {
      "track": "Situation",
      "artists": "Don Toliver",
      "durationMs": 140963,
      "playedAt": "2026-06-22T02:43:34.160Z"
    },
    {
      "track": "Eternal Light",
      "artists": "Free Nationals, Chronixx",
      "durationMs": 193740,
      "playedAt": "2026-06-22T02:41:19.221Z"
    },
    {
      "track": "Plastic 100°C",
      "artists": "Sampha",
      "durationMs": 316187,
      "playedAt": "2026-06-22T02:38:10.863Z"
    },
    {
      "track": "CIRCUS MAXIMUS (feat. The Weeknd & Swae Lee)",
      "artists": "Travis Scott, The Weeknd, Swae Lee",
      "durationMs": 258842,
      "playedAt": "2026-06-22T02:33:00.369Z"
    },
    {
      "track": "IGOR'S THEME",
      "artists": "Tyler, The Creator",
      "durationMs": 200684,
      "playedAt": "2026-06-22T02:28:47.265Z"
    },
    {
      "track": "What If You Hypnotise Me?",
      "artists": "Sampha, Léa Sen",
      "durationMs": 218397,
      "playedAt": "2026-06-22T02:25:32.265Z"
    },
    {
      "track": "One Night Only",
      "artists": "Sonder",
      "durationMs": 195909,
      "playedAt": "2026-06-22T02:21:59.667Z"
    },
    {
      "track": "Beauty & Essex (feat. Daniel Caesar & Unknown Mortal Orchestra)",
      "artists": "Free Nationals, Daniel Caesar, Unknown Mortal Orchestra",
      "durationMs": 277046,
      "playedAt": "2026-06-22T02:18:49.471Z"
    },
    {
      "track": "Nights",
      "artists": "Frank Ocean",
      "durationMs": 307151,
      "playedAt": "2026-06-22T02:14:18.083Z"
    },
    {
      "track": "Pretty Sweet",
      "artists": "Frank Ocean",
      "durationMs": 158478,
      "playedAt": "2026-06-22T02:05:43.072Z"
    },
    {
      "track": "Ivy",
      "artists": "Frank Ocean",
      "durationMs": 249191,
      "playedAt": "2026-06-22T02:03:02.972Z"
    },
    {
      "track": "White Ferrari",
      "artists": "Frank Ocean",
      "durationMs": 248807,
      "playedAt": "2026-06-22T01:58:51.572Z"
    },
    {
      "track": "Self Control",
      "artists": "Frank Ocean",
      "durationMs": 249667,
      "playedAt": "2026-06-22T01:54:48.477Z"
    },
    {
      "track": "Silk & Cologne (EI8HT & Offset) - Spider-Verse Remix",
      "artists": "EI8HT, Offset",
      "durationMs": 162280,
      "playedAt": "2026-06-21T23:46:11.072Z"
    },
    {
      "track": "Mojo So Dope",
      "artists": "Kid Cudi",
      "durationMs": 210586,
      "playedAt": "2026-06-21T23:43:34.516Z"
    },
    {
      "track": "The Running Man",
      "artists": "Vince Staples",
      "durationMs": 202266,
      "playedAt": "2026-06-21T23:40:09.571Z"
    },
    {
      "track": "Just the Right Song",
      "artists": "Vansire",
      "durationMs": 186253,
      "playedAt": "2026-06-21T23:36:53.067Z"
    },
    {
      "track": "Stars",
      "artists": "PinkPantheress",
      "durationMs": 141866,
      "playedAt": "2026-06-21T23:33:52.475Z"
    },
    {
      "track": "DARE (feat. Shaun Ryder & Roses Gabor)",
      "artists": "Gorillaz, Shaun Ryder, Roses Gabor",
      "durationMs": 244999,
      "playedAt": "2026-06-21T23:30:53.374Z"
    },
    {
      "track": "Bones",
      "artists": "Crumb",
      "durationMs": 193981,
      "playedAt": "2026-06-21T20:29:37.847Z"
    },
    {
      "track": "Genie",
      "artists": "Crumb",
      "durationMs": 348706,
      "playedAt": "2026-06-21T20:26:29.402Z"
    },
    {
      "track": "Call On Me",
      "artists": "Daniel Caesar",
      "durationMs": 169004,
      "playedAt": "2026-06-21T20:20:46.413Z"
    },
    {
      "track": "Ensenada",
      "artists": "Sublime",
      "durationMs": 154484,
      "playedAt": "2026-06-21T20:18:03.049Z"
    },
    {
      "track": "Sign Of The Times",
      "artists": "Daniel Caesar",
      "durationMs": 231800,
      "playedAt": "2026-06-21T20:15:34.356Z"
    },
    {
      "track": "Just How You Are",
      "artists": "Leon Thomas",
      "durationMs": 194247,
      "playedAt": "2026-06-21T20:11:48.257Z"
    },
    {
      "track": "Husk",
      "artists": "Men I Trust",
      "durationMs": 204651,
      "playedAt": "2026-06-21T20:08:39.717Z"
    },
    {
      "track": "Run Your Mouth",
      "artists": "The Marías",
      "durationMs": 160000,
      "playedAt": "2026-06-21T20:05:20.842Z"
    },
    {
      "track": "Many Times",
      "artists": "Dijon",
      "durationMs": 126905,
      "playedAt": "2026-06-21T20:02:46.526Z"
    },
    {
      "track": "Many Times",
      "artists": "Dijon",
      "durationMs": 126905,
      "playedAt": "2026-06-21T19:50:11.659Z"
    },
    {
      "track": "4EVER",
      "artists": "Clairo",
      "durationMs": 159595,
      "playedAt": "2026-06-21T19:31:24.565Z"
    },
    {
      "track": "Fauxllennium",
      "artists": "TV Girl, George Clanton",
      "durationMs": 188533,
      "playedAt": "2026-06-21T19:28:50.460Z"
    },
    {
      "track": "Billie Toppy",
      "artists": "Men I Trust",
      "durationMs": 195289,
      "playedAt": "2026-06-21T19:25:47.655Z"
    },
    {
      "track": "PUNK ROCKY",
      "artists": "A$AP Rocky",
      "durationMs": 235344,
      "playedAt": "2026-06-21T19:22:38.259Z"
    },
    {
      "track": "Come Over",
      "artists": "LE SSERAFIM",
      "durationMs": 137178,
      "playedAt": "2026-06-21T19:18:45.160Z"
    },
    {
      "track": "Disciples",
      "artists": "Tame Impala",
      "durationMs": 108546,
      "playedAt": "2026-06-21T19:16:33.765Z"
    },
    {
      "track": "Enter Galactic (Love Connection Part I)",
      "artists": "Kid Cudi",
      "durationMs": 260200,
      "playedAt": "2026-06-21T19:14:50.864Z"
    },
    {
      "track": "RIP Young",
      "artists": "Isaiah Rashad",
      "durationMs": 158050,
      "playedAt": "2026-06-21T19:10:36.368Z"
    },
    {
      "track": "Sunshine (feat. Fousheé)",
      "artists": "Steve Lacy, Fousheé",
      "durationMs": 293428,
      "playedAt": "2026-06-21T19:08:03.969Z"
    },
    {
      "track": "Way Bigger",
      "artists": "Don Toliver",
      "durationMs": 196011,
      "playedAt": "2026-06-21T19:03:16.281Z"
    },
    {
      "track": "Sugar",
      "artists": "Men I Trust",
      "durationMs": 176315,
      "playedAt": "2026-06-21T19:00:06Z"
    },
    {
      "track": "Changes",
      "artists": "Empire Of The Sun",
      "durationMs": 218179,
      "playedAt": "2026-06-21T18:57:15.379Z"
    },
    {
      "track": "The Complete Knock",
      "artists": "Blood Orange",
      "durationMs": 303533,
      "playedAt": "2026-06-21T18:53:42.946Z"
    },
    {
      "track": "Simulation Swarm",
      "artists": "Big Thief",
      "durationMs": 252733,
      "playedAt": "2026-06-21T18:48:45.131Z"
    },
    {
      "track": "Talk 2 Me",
      "artists": "54 Ultra",
      "durationMs": 186624,
      "playedAt": "2026-06-21T18:44:38.024Z"
    },
    {
      "track": "Warning Sign",
      "artists": "Hannah Jadagu",
      "durationMs": 206012,
      "playedAt": "2026-06-21T18:41:37.289Z"
    },
    {
      "track": "In My Years",
      "artists": "Men I Trust",
      "durationMs": 197086,
      "playedAt": "2026-06-21T18:38:16.694Z"
    },
    {
      "track": "Echolalia",
      "artists": "Yves Tumor",
      "durationMs": 180146,
      "playedAt": "2026-06-21T18:35:05.294Z"
    },
    {
      "track": "Gospel For A New Century",
      "artists": "Yves Tumor",
      "durationMs": 198626,
      "playedAt": "2026-06-21T18:32:10.934Z"
    },
    {
      "track": "Loser",
      "artists": "Tame Impala",
      "durationMs": 223069,
      "playedAt": "2026-06-21T18:28:57.968Z"
    },
    {
      "track": "Vinta",
      "artists": "Crumb",
      "durationMs": 299970,
      "playedAt": "2026-06-21T18:25:20.636Z"
    },
    {
      "track": "Human Happens",
      "artists": "Magdalena Bay",
      "durationMs": 243053,
      "playedAt": "2026-06-21T18:20:26.531Z"
    },
    {
      "track": "Another Stone",
      "artists": "Men I Trust",
      "durationMs": 190280,
      "playedAt": "2026-06-21T18:16:29.036Z"
    },
    {
      "track": "My Love",
      "artists": "Hannah Jadagu",
      "durationMs": 164956,
      "playedAt": "2026-06-21T18:13:24.521Z"
    },
    {
      "track": "Afterthought",
      "artists": "Tame Impala",
      "durationMs": 241783,
      "playedAt": "2026-06-21T18:10:45.273Z"
    },
    {
      "track": "Fantasy (feat. Don Toliver)",
      "artists": "Kali Uchis, Don Toliver",
      "durationMs": 178274,
      "playedAt": "2026-06-21T18:06:49.137Z"
    },
    {
      "track": "Radio",
      "artists": "Bershy",
      "durationMs": 201853,
      "playedAt": "2026-06-21T18:03:42.762Z"
    },
    {
      "track": "‘87 Stingray",
      "artists": "Tory Lanez",
      "durationMs": 141333,
      "playedAt": "2026-06-21T17:58:18.613Z"
    },
    {
      "track": "Wrong Places",
      "artists": "Lauren Creviston, Brynn Elise",
      "durationMs": 207428,
      "playedAt": "2026-06-21T17:52:48.351Z"
    },
    {
      "track": "ROCKMAN",
      "artists": "Mk.gee",
      "durationMs": 179370,
      "playedAt": "2026-06-21T17:49:26.650Z"
    },
    {
      "track": "I am not a Lyricist",
      "artists": "Baby Keem",
      "durationMs": 205176,
      "playedAt": "2026-06-21T17:46:33.050Z"
    },
    {
      "track": "Dramatic Girl (feat. Che Ecru)",
      "artists": "Baby Keem, Che Ecru",
      "durationMs": 199831,
      "playedAt": "2026-06-21T17:43:13.452Z"
    },
    {
      "track": "Kompany",
      "artists": "monte booker, Smino, Phoelix",
      "durationMs": 209868,
      "playedAt": "2026-06-21T17:39:59.551Z"
    },
    {
      "track": "Best to You",
      "artists": "Blood Orange, Empress Of",
      "durationMs": 225747,
      "playedAt": "2026-06-21T17:36:35.155Z"
    },
    {
      "track": "Humans",
      "artists": "Night Tapes",
      "durationMs": 251690,
      "playedAt": "2026-06-21T17:32:55.154Z"
    },
    {
      "track": "swordsman",
      "artists": "Night Tapes",
      "durationMs": 208075,
      "playedAt": "2026-06-21T17:28:49.163Z"
    },
    {
      "track": "drifting",
      "artists": "Night Tapes",
      "durationMs": 212440,
      "playedAt": "2026-06-21T17:25:26.928Z"
    },
    {
      "track": "Dræm Girl",
      "artists": "No Vacation",
      "durationMs": 234631,
      "playedAt": "2026-06-21T17:22:00.273Z"
    },
    {
      "track": "Humans",
      "artists": "Night Tapes",
      "durationMs": 251690,
      "playedAt": "2026-06-21T17:05:08.194Z"
    },
    {
      "track": "swordsman",
      "artists": "Night Tapes",
      "durationMs": 208075,
      "playedAt": "2026-06-21T15:19:53.278Z"
    },
    {
      "track": "drifting",
      "artists": "Night Tapes",
      "durationMs": 212440,
      "playedAt": "2026-06-21T15:16:30.674Z"
    },
    {
      "track": "Dræm Girl",
      "artists": "No Vacation",
      "durationMs": 234631,
      "playedAt": "2026-06-21T15:13:03.990Z"
    },
    {
      "track": "Dangerous",
      "artists": "Big Data, Joywave",
      "durationMs": 280426,
      "playedAt": "2026-06-21T15:09:19.285Z"
    },
    {
      "track": "Channel 4",
      "artists": "Yot Club",
      "durationMs": 171274,
      "playedAt": "2026-06-21T15:04:13.159Z"
    },
    {
      "track": "Go Away",
      "artists": "Yot Club",
      "durationMs": 161941,
      "playedAt": "2026-06-21T15:01:26.895Z"
    },
    {
      "track": "CHANCES",
      "artists": "KAYTRANADA, Shay Lia",
      "durationMs": 218187,
      "playedAt": "2026-06-21T14:58:49.953Z"
    },
    {
      "track": "BOY IN RED",
      "artists": "Isaiah Rashad, SZA",
      "durationMs": 189964,
      "playedAt": "2026-06-21T14:55:16.758Z"
    },
    {
      "track": "M.O.M.",
      "artists": "Isaiah Rashad",
      "durationMs": 165576,
      "playedAt": "2026-06-21T14:52:11.800Z"
    },
    {
      "track": "SUPAFICIAL",
      "artists": "Isaiah Rashad",
      "durationMs": 284813,
      "playedAt": "2026-06-21T14:49:31.211Z"
    },
    {
      "track": "SCARED 2 LOOK DOWN",
      "artists": "Isaiah Rashad",
      "durationMs": 216278,
      "playedAt": "2026-06-21T14:44:51.402Z"
    },
    {
      "track": "Undercover Martyn",
      "artists": "Two Door Cinema Club",
      "durationMs": 167773,
      "playedAt": "2026-06-21T14:41:03.478Z"
    },
    {
      "track": "Tailwhip",
      "artists": "Men I Trust",
      "durationMs": 225263,
      "playedAt": "2026-06-21T02:39:00.237Z"
    },
    {
      "track": "Better in the Dark",
      "artists": "Jordana, TV Girl",
      "durationMs": 155500,
      "playedAt": "2026-06-21T02:35:14.090Z"
    },
    {
      "track": "Top Dog",
      "artists": "Magdalena Bay",
      "durationMs": 137187,
      "playedAt": "2026-06-21T02:32:29.689Z"
    },
    {
      "track": "DHL",
      "artists": "Frank Ocean",
      "durationMs": 268893,
      "playedAt": "2026-06-21T02:30:06.488Z"
    },
    {
      "track": "X-Wing - Cold Blooded Soul Version",
      "artists": "Denzel Curry",
      "durationMs": 186280,
      "playedAt": "2026-06-21T02:25:43.391Z"
    },
    {
      "track": "SKELETONS",
      "artists": "Travis Scott",
      "durationMs": 145588,
      "playedAt": "2026-06-21T02:22:42.792Z"
    },
    {
      "track": "Like Him (feat. Lola Young)",
      "artists": "Tyler, The Creator, Lola Young",
      "durationMs": 278014,
      "playedAt": "2026-06-21T02:20:22.882Z"
    },
    {
      "track": "Electioneering",
      "artists": "Radiohead",
      "durationMs": 230626,
      "playedAt": "2026-06-21T02:15:50.637Z"
    },
    {
      "track": "The Divine Chord",
      "artists": "The Avalanches, MGMT, Johnny Marr",
      "durationMs": 187586,
      "playedAt": "2026-06-21T02:12:05.725Z"
    },
    {
      "track": "Mercury",
      "artists": "Steve Lacy",
      "durationMs": 295411,
      "playedAt": "2026-06-21T02:09:03.850Z"
    },
    {
      "track": "Chanel",
      "artists": "Frank Ocean",
      "durationMs": 210285,
      "playedAt": "2026-06-21T02:04:06.014Z"
    },
    {
      "track": "HIGHEST IN THE ROOM",
      "artists": "Travis Scott",
      "durationMs": 175720,
      "playedAt": "2026-06-21T02:00:41.508Z"
    },
    {
      "track": "Rigamortus",
      "artists": "Kendrick Lamar",
      "durationMs": 168591,
      "playedAt": "2026-06-21T01:57:51.507Z"
    },
    {
      "track": "Save Room",
      "artists": "John Legend",
      "durationMs": 235870,
      "playedAt": "2026-06-21T01:55:08.615Z"
    },
    {
      "track": "ROLE MODEL",
      "artists": "Brent Faiyaz",
      "durationMs": 194009,
      "playedAt": "2026-06-21T01:51:18.414Z"
    },
    {
      "track": "COFFEE BEAN",
      "artists": "Travis Scott",
      "durationMs": 209115,
      "playedAt": "2026-06-21T01:48:10.163Z"
    },
    {
      "track": "Dance",
      "artists": "Jay Safari",
      "durationMs": 165485,
      "playedAt": "2026-06-21T01:44:46.688Z"
    },
    {
      "track": "the BLACK seminole.",
      "artists": "Lil Yachty, Diana Gordon",
      "durationMs": 411912,
      "playedAt": "2026-06-21T01:41:55.924Z"
    },
    {
      "track": "Tek It",
      "artists": "Cafuné",
      "durationMs": 191823,
      "playedAt": "2026-06-20T22:40:13.519Z"
    },
    {
      "track": "Sweater Weather",
      "artists": "The Neighbourhood",
      "durationMs": 240400,
      "playedAt": "2026-06-20T22:36:38.658Z"
    },
    {
      "track": "DARE (feat. Shaun Ryder & Roses Gabor)",
      "artists": "Gorillaz, Shaun Ryder, Roses Gabor",
      "durationMs": 244999,
      "playedAt": "2026-06-20T22:32:06.257Z"
    },
    {
      "track": "Bleed (feat. Omar Apollo)",
      "artists": "Malcolm Todd, Omar Apollo",
      "durationMs": 179373,
      "playedAt": "2026-06-20T22:27:54.442Z"
    },
    {
      "track": "waves - Tame Impala Remix",
      "artists": "Miguel, Tame Impala",
      "durationMs": 253346,
      "playedAt": "2026-06-20T22:24:50.677Z"
    },
    {
      "track": "What You Know",
      "artists": "Two Door Cinema Club",
      "durationMs": 191400,
      "playedAt": "2026-06-20T22:20:11.488Z"
    },
    {
      "track": "Disciples",
      "artists": "Tame Impala",
      "durationMs": 108546,
      "playedAt": "2026-06-20T22:16:38.160Z"
    },
    {
      "track": "Come Over",
      "artists": "Kowloon",
      "durationMs": 250543,
      "playedAt": "2026-06-20T22:14:50.964Z"
    },
    {
      "track": "Humans",
      "artists": "Night Tapes",
      "durationMs": 251690,
      "playedAt": "2026-06-20T22:07:45.817Z"
    },
    {
      "track": "Took a While",
      "artists": "NEIL FRANCES",
      "durationMs": 202909,
      "playedAt": "2026-06-20T22:03:39.824Z"
    },
    {
      "track": "HIGHJACK",
      "artists": "A$AP Rocky, Jessica Pratt",
      "durationMs": 190074,
      "playedAt": "2026-06-20T22:00:22.582Z"
    },
    {
      "track": "ORANGE SODA",
      "artists": "Baby Keem",
      "durationMs": 129882,
      "playedAt": "2026-06-20T21:57:18.317Z"
    },
    {
      "track": "Little Sister",
      "artists": "Queens of the Stone Age",
      "durationMs": 174026,
      "playedAt": "2026-06-20T21:55:14.052Z"
    },
    {
      "track": "Dangerous",
      "artists": "Big Data, Joywave",
      "durationMs": 280426,
      "playedAt": "2026-06-20T21:52:25.809Z"
    },
    {
      "track": "Run Your Mouth",
      "artists": "The Marías",
      "durationMs": 160000,
      "playedAt": "2026-06-20T21:47:51.015Z"
    },
    {
      "track": "Hurts Me",
      "artists": "Tory Lanez, Trippie Redd, Yoko Gold",
      "durationMs": 140800,
      "playedAt": "2026-06-20T21:45:16.813Z"
    },
    {
      "track": "Player Two - From \"Don't Tell Mom The Babysitter's Dead\"",
      "artists": "Jordan Ward",
      "durationMs": 158057,
      "playedAt": "2026-06-20T21:43:01.717Z"
    },
    {
      "track": "Let Her Go (feat. James Blake)",
      "artists": "Don Toliver, James Blake",
      "durationMs": 192720,
      "playedAt": "2026-06-20T19:31:33.723Z"
    },
    {
      "track": "Dominoes",
      "artists": "Jungle",
      "durationMs": 177520,
      "playedAt": "2026-06-20T19:28:20.930Z"
    },
    {
      "track": "All Caps",
      "artists": "Madvillain, Madlib, MF DOOM",
      "durationMs": 130479,
      "playedAt": "2026-06-20T19:24:33.041Z"
    },
    {
      "track": "Enter Galactic (Love Connection Part I)",
      "artists": "Kid Cudi",
      "durationMs": 260200,
      "playedAt": "2026-06-20T19:22:28.343Z"
    },
    {
      "track": "Summer 2000 Baby",
      "artists": "TV Girl, George Clanton",
      "durationMs": 242410,
      "playedAt": "2026-06-20T19:18:05.443Z"
    },
    {
      "track": "Waltzing Back",
      "artists": "No Vacation",
      "durationMs": 192000,
      "playedAt": "2026-06-20T19:14:08.744Z"
    },
    {
      "track": "Apparently",
      "artists": "J. Cole",
      "durationMs": 292865,
      "playedAt": "2026-06-20T19:11:02.356Z"
    },
    {
      "track": "On My Own",
      "artists": "Jaden, Kid Cudi",
      "durationMs": 244720,
      "playedAt": "2026-06-20T19:06:15.154Z"
    },
    {
      "track": "Hunnybee",
      "artists": "Unknown Mortal Orchestra",
      "durationMs": 268333,
      "playedAt": "2026-06-20T19:02:16.257Z"
    },
    {
      "track": "Less Than Zero",
      "artists": "The Weeknd",
      "durationMs": 211814,
      "playedAt": "2026-06-20T18:57:53.551Z"
    },
    {
      "track": "These Walls",
      "artists": "Kendrick Lamar, Bilal, Anna Wise, Thundercat",
      "durationMs": 248682,
      "playedAt": "2026-06-20T18:54:24.855Z"
    },
    {
      "track": "Low",
      "artists": "SZA",
      "durationMs": 181080,
      "playedAt": "2026-06-20T18:50:21.823Z"
    },
    {
      "track": "Mr. Rager",
      "artists": "Kid Cudi",
      "durationMs": 294226,
      "playedAt": "2026-06-20T18:47:26.452Z"
    },
    {
      "track": "Mind Mischief",
      "artists": "Tame Impala",
      "durationMs": 271880,
      "playedAt": "2026-06-20T18:42:37.963Z"
    },
    {
      "track": "L.M.F.",
      "artists": "Smino",
      "durationMs": 188500,
      "playedAt": "2026-06-20T18:37:58.460Z"
    },
    {
      "track": "Problemz",
      "artists": "Jungle",
      "durationMs": 184086,
      "playedAt": "2026-06-20T17:42:23.251Z"
    },
    {
      "track": "Little Homies",
      "artists": "Vince Staples",
      "durationMs": 224745,
      "playedAt": "2026-06-20T17:39:24.854Z"
    },
    {
      "track": "Talk Down",
      "artists": "Dijon",
      "durationMs": 151565,
      "playedAt": "2026-06-20T17:35:45.851Z"
    },
    {
      "track": "Human Happens",
      "artists": "Magdalena Bay",
      "durationMs": 243053,
      "playedAt": "2026-06-20T17:33:19.955Z"
    },
    {
      "track": "Cudi Zone",
      "artists": "Kid Cudi",
      "durationMs": 259040,
      "playedAt": "2026-06-20T17:29:22.656Z"
    },
    {
      "track": "Outta My Head (with John Mayer)",
      "artists": "Khalid, John Mayer",
      "durationMs": 177106,
      "playedAt": "2026-06-20T17:25:09.384Z"
    },
    {
      "track": "Colors",
      "artists": "Chenayder, MAVI",
      "durationMs": 186666,
      "playedAt": "2026-06-20T17:22:09.665Z"
    },
    {
      "track": "SUPAFICIAL",
      "artists": "Isaiah Rashad",
      "durationMs": 284813,
      "playedAt": "2026-06-20T17:19:11.665Z"
    },
    {
      "track": "Simulation Swarm",
      "artists": "Big Thief",
      "durationMs": 252733,
      "playedAt": "2026-06-20T17:14:32.655Z"
    },
    {
      "track": "Radio",
      "artists": "Bershy",
      "durationMs": 201853,
      "playedAt": "2026-06-20T17:10:25.555Z"
    },
    {
      "track": "Many Times",
      "artists": "Dijon",
      "durationMs": 126905,
      "playedAt": "2026-06-20T17:07:09.491Z"
    },
    {
      "track": "The Running Man",
      "artists": "Vince Staples",
      "durationMs": 202266,
      "playedAt": "2026-06-20T17:04:47.308Z"
    },
    {
      "track": "Just the Right Song",
      "artists": "Vansire",
      "durationMs": 186253,
      "playedAt": "2026-06-20T17:01:35.457Z"
    },
    {
      "track": "Stars",
      "artists": "PinkPantheress",
      "durationMs": 141866,
      "playedAt": "2026-06-20T16:58:34.958Z"
    },
    {
      "track": "Cotton",
      "artists": "Vince Staples",
      "durationMs": 223800,
      "playedAt": "2026-06-20T16:56:18.759Z"
    },
    {
      "track": "The Big Bad Wolf",
      "artists": "Vince Staples",
      "durationMs": 132413,
      "playedAt": "2026-06-20T16:52:40.658Z"
    },
    {
      "track": "Stateside + Zara Larsson",
      "artists": "PinkPantheress, Zara Larsson",
      "durationMs": 184761,
      "playedAt": "2026-06-20T16:50:33.957Z"
    },
    {
      "track": "Girl Like Me",
      "artists": "PinkPantheress",
      "durationMs": 145520,
      "playedAt": "2026-06-20T16:47:34.898Z"
    },
    {
      "track": "Bags",
      "artists": "Clairo",
      "durationMs": 260519,
      "playedAt": "2026-06-20T16:45:15.120Z"
    },
    {
      "track": "Eyes Off You",
      "artists": "Tokyo Tea Room",
      "durationMs": 182480,
      "playedAt": "2026-06-20T16:41:00.351Z"
    },
    {
      "track": "Alive",
      "artists": "Empire Of The Sun",
      "durationMs": 204546,
      "playedAt": "2026-06-20T16:38:03.561Z"
    },
    {
      "track": "Tek It",
      "artists": "Cafuné",
      "durationMs": 191823,
      "playedAt": "2026-06-20T16:32:07.764Z"
    },
    {
      "track": "Apparently",
      "artists": "J. Cole",
      "durationMs": 292865,
      "playedAt": "2026-06-20T16:23:34.712Z"
    },
    {
      "track": "booman",
      "artists": "Baby Keem",
      "durationMs": 155153,
      "playedAt": "2026-06-20T01:19:27.499Z"
    },
    {
      "track": "Billie Toppy",
      "artists": "Men I Trust",
      "durationMs": 195289,
      "playedAt": "2026-06-20T01:16:58.097Z"
    },
    {
      "track": "Stars",
      "artists": "PinkPantheress",
      "durationMs": 141866,
      "playedAt": "2026-06-20T01:13:20.122Z"
    },
    {
      "track": "BUTTERFLY EFFECT",
      "artists": "Travis Scott",
      "durationMs": 190557,
      "playedAt": "2026-06-20T00:07:32.126Z"
    },
    {
      "track": "Superpowers",
      "artists": "Daniel Caesar",
      "durationMs": 174512,
      "playedAt": "2026-06-20T00:04:27.226Z"
    },
    {
      "track": "New Person, Same Old Mistakes",
      "artists": "Tame Impala",
      "durationMs": 363240,
      "playedAt": "2026-06-20T00:01:30.244Z"
    },
    {
      "track": "California",
      "artists": "beabadoobee",
      "durationMs": 172293,
      "playedAt": "2026-06-19T23:23:38.171Z"
    },
    {
      "track": "SKELETONS",
      "artists": "Travis Scott",
      "durationMs": 145588,
      "playedAt": "2026-06-19T23:20:51.586Z"
    },
    {
      "track": "Better in the Dark",
      "artists": "Jordana, TV Girl",
      "durationMs": 155500,
      "playedAt": "2026-06-19T23:18:31.652Z"
    },
    {
      "track": "She Knows This",
      "artists": "Kid Cudi",
      "durationMs": 216560,
      "playedAt": "2026-06-19T23:16:01.915Z"
    },
    {
      "track": "the BLACK seminole.",
      "artists": "Lil Yachty, Diana Gordon",
      "durationMs": 411912,
      "playedAt": "2026-06-19T23:12:08.384Z"
    },
    {
      "track": "Say, Can You Hear",
      "artists": "Men I Trust",
      "durationMs": 189246,
      "playedAt": "2026-06-19T23:05:08.794Z"
    },
    {
      "track": "Sacrifice",
      "artists": "The Weeknd",
      "durationMs": 188918,
      "playedAt": "2026-06-19T23:02:07.982Z"
    },
    {
      "track": "the perfect pair",
      "artists": "beabadoobee",
      "durationMs": 177533,
      "playedAt": "2026-06-19T22:59:04.790Z"
    },
    {
      "track": "RIP",
      "artists": "Miguel",
      "durationMs": 164692,
      "playedAt": "2026-06-19T22:56:12.930Z"
    },
    {
      "track": "Cigarettes out the Window",
      "artists": "TV Girl",
      "durationMs": 198960,
      "playedAt": "2026-06-19T22:52:56.584Z"
    },
    {
      "track": "The Complete Knock",
      "artists": "Blood Orange",
      "durationMs": 303533,
      "playedAt": "2026-06-19T22:49:43.413Z"
    },
    {
      "track": "Babydoll",
      "artists": "Dominic Fike",
      "durationMs": 97960,
      "playedAt": "2026-06-19T22:44:45.586Z"
    },
    {
      "track": "‘87 Stingray",
      "artists": "Tory Lanez",
      "durationMs": 141333,
      "playedAt": "2026-06-19T22:43:13.279Z"
    },
    {
      "track": "Memories",
      "artists": "Thutmose",
      "durationMs": 199146,
      "playedAt": "2026-06-19T22:40:34.945Z"
    },
    {
      "track": "Helmet",
      "artists": "Steve Lacy",
      "durationMs": 201510,
      "playedAt": "2026-06-19T22:37:21.434Z"
    },
    {
      "track": "Landline",
      "artists": "binki",
      "durationMs": 160329,
      "playedAt": "2026-06-19T22:34:05.615Z"
    },
    {
      "track": "Un Millón",
      "artists": "The Marías",
      "durationMs": 167386,
      "playedAt": "2026-06-19T22:31:04.481Z"
    },
    {
      "track": "Mojo So Dope",
      "artists": "Kid Cudi",
      "durationMs": 210586,
      "playedAt": "2026-06-19T22:28:07.183Z"
    },
    {
      "track": "Outta My Head (with John Mayer)",
      "artists": "Khalid, John Mayer",
      "durationMs": 177106,
      "playedAt": "2026-06-19T22:24:42.287Z"
    },
    {
      "track": "Image",
      "artists": "Magdalena Bay",
      "durationMs": 212866,
      "playedAt": "2026-06-19T22:21:29.587Z"
    },
    {
      "track": "Simulation Swarm",
      "artists": "Big Thief",
      "durationMs": 252733,
      "playedAt": "2026-06-19T22:18:02.468Z"
    },
    {
      "track": "booman",
      "artists": "Baby Keem",
      "durationMs": 155153,
      "playedAt": "2026-06-19T22:13:13.190Z"
    },
    {
      "track": "Low",
      "artists": "SZA",
      "durationMs": 181080,
      "playedAt": "2026-06-19T18:58:58.610Z"
    },
    {
      "track": "Hurts Me",
      "artists": "Tory Lanez, Trippie Redd, Yoko Gold",
      "durationMs": 140800,
      "playedAt": "2026-06-19T18:52:19.207Z"
    },
    {
      "track": "Sweet Life",
      "artists": "Frank Ocean",
      "durationMs": 262680,
      "playedAt": "2026-06-19T18:50:07.011Z"
    },
    {
      "track": "Basement Jack",
      "artists": "Steve Lacy",
      "durationMs": 109818,
      "playedAt": "2026-06-19T18:45:50.044Z"
    },
    {
      "track": "Looking Out for You",
      "artists": "Joy Again",
      "durationMs": 179499,
      "playedAt": "2026-06-19T18:44:06.014Z"
    },
    {
      "track": "Mind Fields",
      "artists": "No Vacation",
      "durationMs": 272625,
      "playedAt": "2026-06-19T18:41:06.382Z"
    },
    {
      "track": "Wake Up",
      "artists": "Kowloon",
      "durationMs": 239351,
      "playedAt": "2026-06-19T18:36:42.118Z"
    },
    {
      "track": "Wake Up",
      "artists": "Kowloon",
      "durationMs": 239351,
      "playedAt": "2026-06-19T18:35:08.853Z"
    },
    {
      "track": "The Beginning",
      "artists": "Magdalena Bay",
      "durationMs": 241304,
      "playedAt": "2026-06-19T12:27:52.224Z"
    },
    {
      "track": "Many Times",
      "artists": "Dijon",
      "durationMs": 126905,
      "playedAt": "2026-06-19T12:23:46.179Z"
    },
    {
      "track": "My Muse",
      "artists": "Leon Thomas",
      "durationMs": 165599,
      "playedAt": "2026-06-19T12:21:45.028Z"
    },
    {
      "track": "Talk 2 Me",
      "artists": "54 Ultra",
      "durationMs": 186624,
      "playedAt": "2026-06-19T12:15:51.082Z"
    },
    {
      "track": "Tek It",
      "artists": "Cafuné",
      "durationMs": 191823,
      "playedAt": "2026-06-19T12:12:34.533Z"
    },
    {
      "track": "Some",
      "artists": "Steve Lacy",
      "durationMs": 118393,
      "playedAt": "2026-06-19T03:30:56.732Z"
    },
    {
      "track": "Fantasy (feat. Don Toliver)",
      "artists": "Kali Uchis, Don Toliver",
      "durationMs": 178274,
      "playedAt": "2026-06-19T01:38:48.194Z"
    },
    {
      "track": "My Old Ways",
      "artists": "Tame Impala",
      "durationMs": 298783,
      "playedAt": "2026-06-19T01:35:55.558Z"
    },
    {
      "track": "Antidote",
      "artists": "Orion Sun",
      "durationMs": 169822,
      "playedAt": "2026-06-19T01:31:02.500Z"
    },
    {
      "track": "A New Kind Of Love - Demo",
      "artists": "Frou Frou, Imogen Heap, Guy Sigsworth",
      "durationMs": 259071,
      "playedAt": "2026-06-19T01:28:18.405Z"
    },
    {
      "track": "Stars",
      "artists": "PinkPantheress",
      "durationMs": 141866,
      "playedAt": "2026-06-19T01:23:50.299Z"
    },
    {
      "track": "Cotton",
      "artists": "Vince Staples",
      "durationMs": 223800,
      "playedAt": "2026-06-18T23:40:08.468Z"
    },
    {
      "track": "The Big Bad Wolf",
      "artists": "Vince Staples",
      "durationMs": 132413,
      "playedAt": "2026-06-18T21:25:58.535Z"
    },
    {
      "track": "Stateside + Zara Larsson",
      "artists": "PinkPantheress, Zara Larsson",
      "durationMs": 184761,
      "playedAt": "2026-06-18T21:23:51.848Z"
    },
    {
      "track": "Girl Like Me",
      "artists": "PinkPantheress",
      "durationMs": 145520,
      "playedAt": "2026-06-18T21:20:52.801Z"
    },
    {
      "track": "Bags",
      "artists": "Clairo",
      "durationMs": 260519,
      "playedAt": "2026-06-18T21:18:33.049Z"
    },
    {
      "track": "Alive",
      "artists": "Empire Of The Sun",
      "durationMs": 204546,
      "playedAt": "2026-06-18T21:14:11.152Z"
    },
    {
      "track": "Tek It",
      "artists": "Cafuné",
      "durationMs": 191823,
      "playedAt": "2026-06-18T21:10:52.248Z"
    },
    {
      "track": "Little Dark Age",
      "artists": "MGMT",
      "durationMs": 299933,
      "playedAt": "2026-06-18T21:07:08.544Z"
    },
    {
      "track": "Badfish",
      "artists": "Sublime",
      "durationMs": 188085,
      "playedAt": "2026-06-18T21:02:14.355Z"
    },
    {
      "track": "Dream police",
      "artists": "Mk.gee",
      "durationMs": 169519,
      "playedAt": "2026-06-18T20:59:11.960Z"
    },
    {
      "track": "The Prayer",
      "artists": "Kid Cudi",
      "durationMs": 219093,
      "playedAt": "2026-06-18T20:56:28.113Z"
    },
    {
      "track": "That Life",
      "artists": "Unknown Mortal Orchestra",
      "durationMs": 215866,
      "playedAt": "2026-06-18T20:52:54.799Z"
    },
    {
      "track": "Let It Happen",
      "artists": "Tame Impala",
      "durationMs": 467586,
      "playedAt": "2026-06-18T20:49:24.665Z"
    },
    {
      "track": "Let It Happen",
      "artists": "Tame Impala",
      "durationMs": 467586,
      "playedAt": "2026-06-18T20:48:25.828Z"
    },
    {
      "track": "All My Time Is Wasted",
      "artists": "Hannah Jadagu",
      "durationMs": 200853,
      "playedAt": "2026-06-18T12:27:59.488Z"
    },
    {
      "track": "The Moment",
      "artists": "Tame Impala",
      "durationMs": 255413,
      "playedAt": "2026-06-18T12:24:37.275Z"
    },
    {
      "track": "Hold It Together",
      "artists": "The Marías",
      "durationMs": 222021,
      "playedAt": "2026-06-18T12:20:17.272Z"
    },
    {
      "track": "HIGHJACK",
      "artists": "A$AP Rocky, Jessica Pratt",
      "durationMs": 190074,
      "playedAt": "2026-06-18T12:16:41.021Z"
    },
    {
      "track": "Ghost Town",
      "artists": "Kanye West, PARTYNEXTDOOR",
      "durationMs": 271386,
      "playedAt": "2026-06-18T12:13:36.579Z"
    },
    {
      "track": "BOY IN RED",
      "artists": "Isaiah Rashad, SZA",
      "durationMs": 189964,
      "playedAt": "2026-06-18T12:09:10.983Z"
    },
    {
      "track": "BOY IN RED",
      "artists": "Isaiah Rashad, SZA",
      "durationMs": 189964,
      "playedAt": "2026-06-18T10:33:57.946Z"
    },
    {
      "track": "In My Years",
      "artists": "Men I Trust",
      "durationMs": 197086,
      "playedAt": "2026-06-18T03:21:22.076Z"
    },
    {
      "track": "Static",
      "artists": "Steve Lacy",
      "durationMs": 156538,
      "playedAt": "2026-06-18T03:18:10.698Z"
    },
    {
      "track": "I Smoked Away My Brain (I'm God x Demons Mashup) (feat. Imogen Heap & Clams Casino)",
      "artists": "A$AP Rocky, Imogen Heap, Clams Casino",
      "durationMs": 190285,
      "playedAt": "2026-06-18T03:15:39.854Z"
    },
    {
      "track": "Parking Lot",
      "artists": "Anderson .Paak",
      "durationMs": 234333,
      "playedAt": "2026-06-18T03:03:33.747Z"
    },
    {
      "track": "Righteous Minds",
      "artists": "Joey Bada$$",
      "durationMs": 224042,
      "playedAt": "2026-06-18T02:59:45.159Z"
    },
    {
      "track": "Radio",
      "artists": "Bershy",
      "durationMs": 201853,
      "playedAt": "2026-06-18T02:56:06.755Z"
    },
    {
      "track": "Husk",
      "artists": "Men I Trust",
      "durationMs": 204651,
      "playedAt": "2026-06-18T02:52:48.145Z"
    },
    {
      "track": "Garden Shed (feat. Estelle)",
      "artists": "Tyler, The Creator, Estelle",
      "durationMs": 223946,
      "playedAt": "2026-06-18T02:48:33.151Z"
    },
    {
      "track": "Unfuckwittable",
      "artists": "Kid Cudi",
      "durationMs": 275746,
      "playedAt": "2026-06-18T02:44:54.865Z"
    },
    {
      "track": "WE SAW THE SUN!",
      "artists": "Lil Yachty",
      "durationMs": 331428,
      "playedAt": "2026-06-18T02:40:24.858Z"
    },
    {
      "track": "Taking What's Not Yours",
      "artists": "TV Girl",
      "durationMs": 205650,
      "playedAt": "2026-06-18T02:34:59.159Z"
    },
    {
      "track": "don't rely on other men",
      "artists": "JPEGMAFIA",
      "durationMs": 171906,
      "playedAt": "2026-06-18T02:31:39.164Z"
    },
    {
      "track": "Suspended",
      "artists": "Sampha",
      "durationMs": 185371,
      "playedAt": "2026-06-18T02:28:52.966Z"
    },
    {
      "track": "Glow",
      "artists": "Alice Phoebe Lou",
      "durationMs": 165412,
      "playedAt": "2026-06-18T02:25:53.399Z"
    },
    {
      "track": "Underworld",
      "artists": "Alice Phoebe Lou",
      "durationMs": 166321,
      "playedAt": "2026-06-18T02:23:13.618Z"
    },
    {
      "track": "Bags",
      "artists": "Clairo",
      "durationMs": 260519,
      "playedAt": "2026-06-18T02:17:43.179Z"
    },
    {
      "track": "Cotton",
      "artists": "Vince Staples",
      "durationMs": 223800,
      "playedAt": "2026-06-18T02:13:28.360Z"
    },
    {
      "track": "Fine Madeline",
      "artists": "Plums",
      "durationMs": 139749,
      "playedAt": "2026-06-18T02:09:50.306Z"
    },
    {
      "track": "Natural",
      "artists": "Shelly",
      "durationMs": 163764,
      "playedAt": "2026-06-18T02:07:36.347Z"
    },
    {
      "track": "Metamodernity",
      "artists": "Vansire",
      "durationMs": 162663,
      "playedAt": "2026-06-18T02:00:18.039Z"
    },
    {
      "track": "Buttons",
      "artists": "Steve Lacy",
      "durationMs": 184972,
      "playedAt": "2026-06-18T01:57:41.040Z"
    },
    {
      "track": "Best to You",
      "artists": "Blood Orange, Empress Of",
      "durationMs": 225747,
      "playedAt": "2026-06-18T01:54:41.843Z"
    },
    {
      "track": "Equal Trouble",
      "artists": "Blue Material",
      "durationMs": 242102,
      "playedAt": "2026-06-18T01:51:01.743Z"
    },
    {
      "track": "Care",
      "artists": "Freak Slug",
      "durationMs": 169847,
      "playedAt": "2026-06-18T01:47:05.339Z"
    },
    {
      "track": "12:34 AM",
      "artists": "Billy Lemos, Omar Apollo, Maxwell Young",
      "durationMs": 127000,
      "playedAt": "2026-06-18T01:44:21.177Z"
    },
    {
      "track": "Go Away",
      "artists": "Yot Club",
      "durationMs": 161941,
      "playedAt": "2026-06-18T01:41:48.993Z"
    },
    {
      "track": "CHANCES",
      "artists": "KAYTRANADA, Shay Lia",
      "durationMs": 218187,
      "playedAt": "2026-06-17T21:28:00.330Z"
    },
    {
      "track": "BOY IN RED",
      "artists": "Isaiah Rashad, SZA",
      "durationMs": 189964,
      "playedAt": "2026-06-17T21:24:27.857Z"
    },
    {
      "track": "Pitch the Baby",
      "artists": "Cocteau Twins",
      "durationMs": 194080,
      "playedAt": "2026-06-17T21:15:09.738Z"
    },
    {
      "track": "Stars",
      "artists": "PinkPantheress",
      "durationMs": 141866,
      "playedAt": "2026-06-17T21:09:11.244Z"
    },
    {
      "track": "Cotton",
      "artists": "Vince Staples",
      "durationMs": 223800,
      "playedAt": "2026-06-17T21:06:54.946Z"
    },
    {
      "track": "The Big Bad Wolf",
      "artists": "Vince Staples",
      "durationMs": 132413,
      "playedAt": "2026-06-17T21:03:16.747Z"
    },
    {
      "track": "Stateside + Zara Larsson",
      "artists": "PinkPantheress, Zara Larsson",
      "durationMs": 184761,
      "playedAt": "2026-06-17T21:01:10.048Z"
    },
    {
      "track": "Girl Like Me",
      "artists": "PinkPantheress",
      "durationMs": 145520,
      "playedAt": "2026-06-17T20:58:11.127Z"
    },
    {
      "track": "Bags",
      "artists": "Clairo",
      "durationMs": 260519,
      "playedAt": "2026-06-17T20:55:51.226Z"
    },
    {
      "track": "Eyes Off You",
      "artists": "Tokyo Tea Room",
      "durationMs": 182480,
      "playedAt": "2026-06-17T20:51:36.455Z"
    },
    {
      "track": "Alive",
      "artists": "Empire Of The Sun",
      "durationMs": 204546,
      "playedAt": "2026-06-17T20:48:39.742Z"
    },
    {
      "track": "Tek It",
      "artists": "Cafuné",
      "durationMs": 191823,
      "playedAt": "2026-06-17T20:45:20.760Z"
    },
    {
      "track": "White Flag",
      "artists": "Vince Staples",
      "durationMs": 154480,
      "playedAt": "2026-06-17T20:37:10.125Z"
    },
    {
      "track": "Blackberry Marmalade",
      "artists": "Vince Staples",
      "durationMs": 232933,
      "playedAt": "2026-06-17T20:34:41.432Z"
    },
    {
      "track": "Blackberry Marmalade",
      "artists": "Vince Staples",
      "durationMs": 232933,
      "playedAt": "2026-06-17T20:33:50.420Z"
    },
    {
      "track": "Forever Yours",
      "artists": "Brent Faiyaz",
      "durationMs": 96368,
      "playedAt": "2026-06-17T18:51:07.242Z"
    },
    {
      "track": "Summer Love",
      "artists": "bLAck pARty",
      "durationMs": 74318,
      "playedAt": "2026-06-17T18:49:39.083Z"
    },
    {
      "track": "Genie",
      "artists": "Crumb",
      "durationMs": 348706,
      "playedAt": "2026-06-17T18:48:30.444Z"
    },
    {
      "track": "Basement Jack",
      "artists": "Steve Lacy",
      "durationMs": 109818,
      "playedAt": "2026-06-17T18:42:25.143Z"
    },
    {
      "track": "3005",
      "artists": "Childish Gambino",
      "durationMs": 234215,
      "playedAt": "2026-06-17T18:34:52.088Z"
    },
    {
      "track": "Fauxllennium",
      "artists": "TV Girl, George Clanton",
      "durationMs": 188533,
      "playedAt": "2026-06-17T18:31:03.605Z"
    },
    {
      "track": "Carried Away",
      "artists": "Men I Trust",
      "durationMs": 207500,
      "playedAt": "2026-06-17T18:27:55.006Z"
    },
    {
      "track": "Love Me Not",
      "artists": "Ravyn Lenae",
      "durationMs": 213466,
      "playedAt": "2026-06-17T18:24:34.090Z"
    },
    {
      "track": "Used (feat. Don Toliver)",
      "artists": "SZA, Don Toliver",
      "durationMs": 146950,
      "playedAt": "2026-06-17T18:21:06.297Z"
    },
    {
      "track": "Why'd You Only Call Me When You're High?",
      "artists": "Arctic Monkeys",
      "durationMs": 161123,
      "playedAt": "2026-06-17T18:18:45.096Z"
    },
    {
      "track": "Mojo So Dope",
      "artists": "Kid Cudi",
      "durationMs": 210586,
      "playedAt": "2026-06-17T18:16:09.712Z"
    },
    {
      "track": "Little Dark Age",
      "artists": "MGMT",
      "durationMs": 299933,
      "playedAt": "2026-06-17T18:12:32.317Z"
    },
    {
      "track": "Echolalia",
      "artists": "Yves Tumor",
      "durationMs": 180146,
      "playedAt": "2026-06-17T18:07:40.310Z"
    },
    {
      "track": "Echolalia",
      "artists": "Yves Tumor",
      "durationMs": 180146,
      "playedAt": "2026-06-17T18:01:58.994Z"
    },
    {
      "track": "Talk 2 Me",
      "artists": "54 Ultra",
      "durationMs": 186624,
      "playedAt": "2026-06-17T12:34:44.794Z"
    },
    {
      "track": "Channel 4",
      "artists": "Yot Club",
      "durationMs": 171274,
      "playedAt": "2026-06-17T12:28:00.110Z"
    },
    {
      "track": "Chk Chk Boom",
      "artists": "Stray Kids",
      "durationMs": 148051,
      "playedAt": "2026-06-17T12:25:14.600Z"
    },
    {
      "track": "Tek It",
      "artists": "Cafuné",
      "durationMs": 191823,
      "playedAt": "2026-06-17T12:22:52.193Z"
    },
    {
      "track": "Cotton",
      "artists": "Vince Staples",
      "durationMs": 223800,
      "playedAt": "2026-06-17T12:19:46.115Z"
    },
    {
      "track": "Stars",
      "artists": "PinkPantheress",
      "durationMs": 141866,
      "playedAt": "2026-06-17T12:16:07.979Z"
    },
    {
      "track": "Bags",
      "artists": "Clairo",
      "durationMs": 260519,
      "playedAt": "2026-06-17T12:13:51.887Z"
    },
    {
      "track": "The Color Violet",
      "artists": "Tory Lanez",
      "durationMs": 226466,
      "playedAt": "2026-06-17T12:09:15.321Z"
    },
    {
      "track": "Sweet Disposition",
      "artists": "The Temper Trap",
      "durationMs": 236466,
      "playedAt": "2026-06-17T03:01:23.028Z"
    },
    {
      "track": "Ryd",
      "artists": "Steve Lacy",
      "durationMs": 140182,
      "playedAt": "2026-06-17T02:57:26.410Z"
    },
    {
      "track": "Cool It",
      "artists": "Dejima",
      "durationMs": 102922,
      "playedAt": "2026-06-17T02:55:13.662Z"
    },
    {
      "track": "Waltzing Back",
      "artists": "No Vacation",
      "durationMs": 192000,
      "playedAt": "2026-06-17T02:53:36.423Z"
    },
    {
      "track": "Hotel Room",
      "artists": "Ax and the Hatchetmen",
      "durationMs": 148887,
      "playedAt": "2026-06-17T02:50:30.179Z"
    },
    {
      "track": "Impostor Syndrome",
      "artists": "Sidney Gish",
      "durationMs": 294260,
      "playedAt": "2026-06-17T00:22:20.193Z"
    },
    {
      "track": "Sundown Syndrome",
      "artists": "Tame Impala",
      "durationMs": 349333,
      "playedAt": "2026-06-17T00:12:45.501Z"
    },
    {
      "track": "ASTROTHUNDER",
      "artists": "Travis Scott",
      "durationMs": 142969,
      "playedAt": "2026-06-16T21:18:17.223Z"
    },
    {
      "track": "Cherry Blossom",
      "artists": "Empire Of The Sun",
      "durationMs": 207587,
      "playedAt": "2026-06-16T21:06:01.424Z"
    },
    {
      "track": "California",
      "artists": "beabadoobee",
      "durationMs": 172293,
      "playedAt": "2026-06-16T21:02:39.626Z"
    },
    {
      "track": "Care",
      "artists": "Freak Slug",
      "durationMs": 169847,
      "playedAt": "2026-06-16T20:59:38.266Z"
    },
    {
      "track": "Metamodernity",
      "artists": "Vansire",
      "durationMs": 162663,
      "playedAt": "2026-06-16T20:56:57.725Z"
    },
    {
      "track": "Pitch the Baby",
      "artists": "Cocteau Twins",
      "durationMs": 194080,
      "playedAt": "2026-06-16T20:54:20.712Z"
    },
    {
      "track": "The Complete Knock",
      "artists": "Blood Orange",
      "durationMs": 303533,
      "playedAt": "2026-06-16T20:50:56.147Z"
    },
    {
      "track": "Hunnybee",
      "artists": "Unknown Mortal Orchestra",
      "durationMs": 268333,
      "playedAt": "2026-06-16T12:40:17.532Z"
    },
    {
      "track": "King Kunta",
      "artists": "Kendrick Lamar",
      "durationMs": 234693,
      "playedAt": "2026-06-16T12:35:54.899Z"
    },
    {
      "track": "drive ME crazy!",
      "artists": "Lil Yachty, Diana Gordon",
      "durationMs": 229804,
      "playedAt": "2026-06-16T12:32:05.855Z"
    },
    {
      "track": "Summer 2000 Baby",
      "artists": "TV Girl, George Clanton",
      "durationMs": 242410,
      "playedAt": "2026-06-16T12:28:21.807Z"
    },
    {
      "track": "DARE (feat. Shaun Ryder & Roses Gabor)",
      "artists": "Gorillaz, Shaun Ryder, Roses Gabor",
      "durationMs": 244999,
      "playedAt": "2026-06-16T12:24:25.067Z"
    },
    {
      "track": "Best to You",
      "artists": "Blood Orange, Empress Of",
      "durationMs": 225747,
      "playedAt": "2026-06-16T12:20:25.869Z"
    },
    {
      "track": "Stars",
      "artists": "PinkPantheress",
      "durationMs": 141866,
      "playedAt": "2026-06-16T12:16:45.816Z"
    },
    {
      "track": "Stateside + Zara Larsson",
      "artists": "PinkPantheress, Zara Larsson",
      "durationMs": 184761,
      "playedAt": "2026-06-16T12:14:29.620Z"
    },
    {
      "track": "Drugs You Should Try It",
      "artists": "Travis Scott",
      "durationMs": 208487,
      "playedAt": "2026-06-16T12:01:49.325Z"
    },
    {
      "track": "E85",
      "artists": "Don Toliver",
      "durationMs": 153181,
      "playedAt": "2026-06-16T03:43:18.870Z"
    },
    {
      "track": "World Domination",
      "artists": "Joey Bada$$",
      "durationMs": 162761,
      "playedAt": "2026-06-16T02:49:48.907Z"
    },
    {
      "track": "Headlock",
      "artists": "Imogen Heap",
      "durationMs": 215338,
      "playedAt": "2026-06-16T00:00:34.504Z"
    },
    {
      "track": "The Mission",
      "artists": "Bakar",
      "durationMs": 191478,
      "playedAt": "2026-06-15T23:57:05.780Z"
    },
    {
      "track": "Just What I Am",
      "artists": "Kid Cudi, King Chip",
      "durationMs": 228026,
      "playedAt": "2026-06-15T23:53:59.983Z"
    },
    {
      "track": "Doin' Time",
      "artists": "Sublime",
      "durationMs": 253840,
      "playedAt": "2026-06-15T23:50:17.634Z"
    },
    {
      "track": "Colors",
      "artists": "Chenayder, MAVI",
      "durationMs": 186666,
      "playedAt": "2026-06-15T23:46:09.587Z"
    },
    {
      "track": "Cudi Zone",
      "artists": "Kid Cudi",
      "durationMs": 259040,
      "playedAt": "2026-06-15T23:43:08.591Z"
    },
    {
      "track": "Balloon (feat. Doechii)",
      "artists": "Tyler, The Creator, Doechii",
      "durationMs": 154261,
      "playedAt": "2026-06-15T20:56:48.418Z"
    },
    {
      "track": "Balloon (feat. Doechii)",
      "artists": "Tyler, The Creator, Doechii",
      "durationMs": 154261,
      "playedAt": "2026-06-15T20:52:56.570Z"
    },
    {
      "track": "LOVE. FEAT. ZACARI.",
      "artists": "Kendrick Lamar, Zacari",
      "durationMs": 213400,
      "playedAt": "2026-06-15T12:23:52.287Z"
    },
    {
      "track": "By Design",
      "artists": "Kid Cudi, André Benjamin",
      "durationMs": 257053,
      "playedAt": "2026-06-15T12:20:24.599Z"
    },
    {
      "track": "Each Day Gets Better",
      "artists": "John Legend",
      "durationMs": 228004,
      "playedAt": "2026-06-15T12:15:50.180Z"
    },
    {
      "track": "Husk",
      "artists": "Men I Trust",
      "durationMs": 204651,
      "playedAt": "2026-06-15T12:12:07.941Z"
    },
    {
      "track": "4th Dimension",
      "artists": "KIDS SEE GHOSTS, Louis Prima",
      "durationMs": 153351,
      "playedAt": "2026-06-15T12:08:43.143Z"
    },
    {
      "track": "That's My Floor",
      "artists": "Magdalena Bay",
      "durationMs": 209800,
      "playedAt": "2026-06-15T12:05:31.388Z"
    },
    {
      "track": "The Big Bad Wolf",
      "artists": "Vince Staples",
      "durationMs": 132413,
      "playedAt": "2026-06-15T12:02:07.296Z"
    },
    {
      "track": "Only",
      "artists": "Sampha",
      "durationMs": 169590,
      "playedAt": "2026-06-15T12:00:00.594Z"
    },
    {
      "track": "Pitch the Baby",
      "artists": "Cocteau Twins",
      "durationMs": 194080,
      "playedAt": "2026-06-15T01:42:08.744Z"
    },
    {
      "track": "The Running Man",
      "artists": "Vince Staples",
      "durationMs": 202266,
      "playedAt": "2026-06-15T01:38:59.665Z"
    },
    {
      "track": "Just the Right Song",
      "artists": "Vansire",
      "durationMs": 186253,
      "playedAt": "2026-06-15T01:35:42.390Z"
    },
    {
      "track": "Stars",
      "artists": "PinkPantheress",
      "durationMs": 141866,
      "playedAt": "2026-06-15T01:32:41.151Z"
    },
    {
      "track": "Cotton",
      "artists": "Vince Staples",
      "durationMs": 223800,
      "playedAt": "2026-06-15T01:30:24.273Z"
    },
    {
      "track": "The Big Bad Wolf",
      "artists": "Vince Staples",
      "durationMs": 132413,
      "playedAt": "2026-06-15T01:26:45.478Z"
    },
    {
      "track": "Stateside + Zara Larsson",
      "artists": "PinkPantheress, Zara Larsson",
      "durationMs": 184761,
      "playedAt": "2026-06-15T01:24:38.067Z"
    },
    {
      "track": "Girl Like Me",
      "artists": "PinkPantheress",
      "durationMs": 145520,
      "playedAt": "2026-06-15T01:21:38.310Z"
    },
    {
      "track": "Bags",
      "artists": "Clairo",
      "durationMs": 260519,
      "playedAt": "2026-06-15T01:19:17.792Z"
    },
    {
      "track": "Eyes Off You",
      "artists": "Tokyo Tea Room",
      "durationMs": 182480,
      "playedAt": "2026-06-15T01:15:02.277Z"
    },
    {
      "track": "Alive",
      "artists": "Empire Of The Sun",
      "durationMs": 204546,
      "playedAt": "2026-06-15T01:12:04.806Z"
    },
    {
      "track": "FAMJAM4000",
      "artists": "Jordan Ward",
      "durationMs": 158133,
      "playedAt": "2026-06-15T01:07:29.322Z"
    },
    {
      "track": "4th Dimension",
      "artists": "KIDS SEE GHOSTS, Louis Prima",
      "durationMs": 153351,
      "playedAt": "2026-06-15T01:04:56.202Z"
    },
    {
      "track": "That's My Floor",
      "artists": "Magdalena Bay",
      "durationMs": 209800,
      "playedAt": "2026-06-15T01:02:27.858Z"
    },
    {
      "track": "The Big Bad Wolf",
      "artists": "Vince Staples",
      "durationMs": 132413,
      "playedAt": "2026-06-15T00:57:30.100Z"
    },
    {
      "track": "Alive",
      "artists": "Empire Of The Sun",
      "durationMs": 204546,
      "playedAt": "2026-06-15T00:55:22.716Z"
    },
    {
      "track": "Only",
      "artists": "Sampha",
      "durationMs": 169590,
      "playedAt": "2026-06-15T00:52:25.014Z"
    },
    {
      "track": "Bleed (feat. Omar Apollo)",
      "artists": "Malcolm Todd, Omar Apollo",
      "durationMs": 179373,
      "playedAt": "2026-06-14T21:07:33.029Z"
    },
    {
      "track": "World Domination",
      "artists": "Joey Bada$$",
      "durationMs": 162761,
      "playedAt": "2026-06-14T21:04:39.335Z"
    },
    {
      "track": "Found (feat. Brent Faiyaz)",
      "artists": "Tems, Brent Faiyaz",
      "durationMs": 209454,
      "playedAt": "2026-06-14T21:01:37.877Z"
    },
    {
      "track": "Got To Be Good",
      "artists": "Gotts Street Park, Pip Millett",
      "durationMs": 159933,
      "playedAt": "2026-06-14T20:58:13.432Z"
    },
    {
      "track": "Check the Rhime",
      "artists": "A Tribe Called Quest",
      "durationMs": 216693,
      "playedAt": "2026-06-14T20:55:38.503Z"
    },
    {
      "track": "Are You Bored Yet? (feat. Clairo)",
      "artists": "Wallows, Clairo",
      "durationMs": 178000,
      "playedAt": "2026-06-14T20:52:06.806Z"
    },
    {
      "track": "Talk 2 Me",
      "artists": "54 Ultra",
      "durationMs": 186624,
      "playedAt": "2026-06-14T20:49:13.800Z"
    },
    {
      "track": "MERCEDES",
      "artists": "Brent Faiyaz",
      "durationMs": 233069,
      "playedAt": "2026-06-14T20:46:12.185Z"
    },
    {
      "track": "m y . l i f e (with 21 Savage & Morray)",
      "artists": "J. Cole, 21 Savage, Morray",
      "durationMs": 218801,
      "playedAt": "2026-06-14T20:42:24.116Z"
    },
    {
      "track": "On My Own",
      "artists": "Jaden, Kid Cudi",
      "durationMs": 244720,
      "playedAt": "2026-06-14T20:38:50.327Z"
    },
    {
      "track": "Stumble",
      "artists": "Kraak & Smaak, Parcels",
      "durationMs": 270720,
      "playedAt": "2026-06-14T20:34:50.597Z"
    },
    {
      "track": "Call On Me",
      "artists": "Daniel Caesar",
      "durationMs": 169004,
      "playedAt": "2026-06-14T20:30:24.893Z"
    },
    {
      "track": "No Idea",
      "artists": "Don Toliver",
      "durationMs": 154424,
      "playedAt": "2026-06-14T20:27:40.881Z"
    },
    {
      "track": "Trust",
      "artists": "Brent Faiyaz",
      "durationMs": 158420,
      "playedAt": "2026-06-14T20:25:11.462Z"
    },
    {
      "track": "Homecoming",
      "artists": "Kanye West, Chris Martin",
      "durationMs": 203493,
      "playedAt": "2026-06-14T20:22:38.046Z"
    },
    {
      "track": "All Caps",
      "artists": "Madvillain, Madlib, MF DOOM",
      "durationMs": 130479,
      "playedAt": "2026-06-14T20:19:19.565Z"
    },
    {
      "track": "Tieduprightnow",
      "artists": "Parcels",
      "durationMs": 249956,
      "playedAt": "2026-06-14T20:17:14.072Z"
    },
    {
      "track": "Outta My Head (with John Mayer)",
      "artists": "Khalid, John Mayer",
      "durationMs": 177106,
      "playedAt": "2026-06-14T20:13:09.138Z"
    },
    {
      "track": "Nonviolent Communication (Metro Boomin & James Blake, A$AP Rocky, 21 Savage)",
      "artists": "Metro Boomin, James Blake, A$AP Rocky, 21 Savage",
      "durationMs": 209533,
      "playedAt": "2026-06-14T20:10:17.031Z"
    },
    {
      "track": "90210 (feat. Kacy Hill)",
      "artists": "Travis Scott, Kacy Hill",
      "durationMs": 339066,
      "playedAt": "2026-06-14T20:06:52.506Z"
    },
    {
      "track": "Heartbeat",
      "artists": "Childish Gambino",
      "durationMs": 269840,
      "playedAt": "2026-06-14T20:01:18.440Z"
    },
    {
      "track": "My Bad",
      "artists": "Khalid",
      "durationMs": 166101,
      "playedAt": "2026-06-14T19:56:53.604Z"
    },
    {
      "track": "Honeymoon",
      "artists": "Don Toliver",
      "durationMs": 184853,
      "playedAt": "2026-06-14T19:54:12.512Z"
    },
    {
      "track": "Lost In Yesterday",
      "artists": "Tame Impala",
      "durationMs": 249586,
      "playedAt": "2026-06-14T19:51:12.677Z"
    },
    {
      "track": "Black&Blue",
      "artists": "Vince Staples",
      "durationMs": 198630,
      "playedAt": "2026-06-14T19:47:08.088Z"
    },
    {
      "track": "Day 'N' Nite (nightmare)",
      "artists": "Kid Cudi",
      "durationMs": 221240,
      "playedAt": "2026-06-14T19:43:54.468Z"
    },
    {
      "track": "Summer's Over",
      "artists": "Jordana, TV Girl",
      "durationMs": 173000,
      "playedAt": "2026-06-14T19:35:09.958Z"
    },
    {
      "track": "The Less I Know The Better",
      "artists": "Tame Impala",
      "durationMs": 216320,
      "playedAt": "2026-06-14T19:32:21.962Z"
    },
    {
      "track": "Wake Up",
      "artists": "Kowloon",
      "durationMs": 239351,
      "playedAt": "2026-06-14T19:28:50.652Z"
    },
    {
      "track": "Forever Yours",
      "artists": "Brent Faiyaz",
      "durationMs": 96368,
      "playedAt": "2026-06-14T19:24:56.314Z"
    },
    {
      "track": "Overdue (with Travis Scott)",
      "artists": "Metro Boomin, Travis Scott",
      "durationMs": 166093,
      "playedAt": "2026-06-14T19:19:47.504Z"
    },
    {
      "track": "Stereo",
      "artists": "John Legend",
      "durationMs": 251302,
      "playedAt": "2026-06-14T19:17:06.432Z"
    },
    {
      "track": "Rapp Snitch Knishes",
      "artists": "MF DOOM, Mr. Fantastik",
      "durationMs": 172893,
      "playedAt": "2026-06-14T19:12:28.760Z"
    },
    {
      "track": "New Person, Same Old Mistakes",
      "artists": "Tame Impala",
      "durationMs": 363240,
      "playedAt": "2026-06-14T19:09:40.886Z"
    },
    {
      "track": "Sugar",
      "artists": "Men I Trust",
      "durationMs": 176315,
      "playedAt": "2026-06-14T19:08:41.307Z"
    },
    {
      "track": "Alive",
      "artists": "Empire Of The Sun",
      "durationMs": 204546,
      "playedAt": "2026-06-14T19:03:42.671Z"
    },
    {
      "track": "The Ways (with Swae Lee)",
      "artists": "Khalid, Swae Lee",
      "durationMs": 238893,
      "playedAt": "2026-06-14T17:51:03.605Z"
    },
    {
      "track": "Vinta",
      "artists": "Crumb",
      "durationMs": 299970,
      "playedAt": "2026-06-14T17:47:02.340Z"
    },
    {
      "track": "Go Away",
      "artists": "Yot Club",
      "durationMs": 161941,
      "playedAt": "2026-06-14T17:42:11.463Z"
    },
    {
      "track": "Alive",
      "artists": "Empire Of The Sun",
      "durationMs": 204546,
      "playedAt": "2026-06-14T17:39:35.277Z"
    },
    {
      "track": "Channel 4",
      "artists": "Yot Club",
      "durationMs": 171274,
      "playedAt": "2026-06-14T17:36:16.375Z"
    },
    {
      "track": "BOY IN RED",
      "artists": "Isaiah Rashad, SZA",
      "durationMs": 189964,
      "playedAt": "2026-06-14T17:32:42.360Z"
    },
    {
      "track": "Stars",
      "artists": "PinkPantheress",
      "durationMs": 141866,
      "playedAt": "2026-06-14T17:29:38.163Z"
    },
    {
      "track": "Cotton",
      "artists": "Vince Staples",
      "durationMs": 223800,
      "playedAt": "2026-06-14T17:27:21.977Z"
    },
    {
      "track": "Cotton",
      "artists": "Vince Staples",
      "durationMs": 223800,
      "playedAt": "2026-06-14T17:25:02.857Z"
    },
    {
      "track": "Stateside + Zara Larsson",
      "artists": "PinkPantheress, Zara Larsson",
      "durationMs": 184761,
      "playedAt": "2026-06-14T14:31:33.113Z"
    },
    {
      "track": "Bags",
      "artists": "Clairo",
      "durationMs": 260519,
      "playedAt": "2026-06-14T14:28:34.071Z"
    },
    {
      "track": "Alive",
      "artists": "Empire Of The Sun",
      "durationMs": 204546,
      "playedAt": "2026-06-14T14:24:19.240Z"
    },
    {
      "track": "the perfect pair",
      "artists": "beabadoobee",
      "durationMs": 177533,
      "playedAt": "2026-06-14T14:21:00.413Z"
    },
    {
      "track": "Bags",
      "artists": "Clairo",
      "durationMs": 260519,
      "playedAt": "2026-06-14T14:18:08.499Z"
    }
  ]
}